ship_plasmid/LICENSE
ship_plasmid/__init__.py
ship_plasmid/conserved_region_stats.py
ship_plasmid/meta.yaml
ship_plasmid/pangenome_analysis.py
ship_plasmid/pipeline.py
ship_plasmid/pipeline_networks.sh
ship_plasmid/plot_networks.py
ship_plasmid/ship.py
ship_plasmid/annotations/__init__.py
ship_plasmid/annotations/databases.py
ship_plasmid/annotations/fasta_handler.py
ship_plasmid/annotations/prokka.py
ship_plasmid/configs/phylo_config.py
ship_plasmid/utils/__init__.py
ship_plasmid/utils/amrfinder.py
ship_plasmid/utils/base_cluster.py
ship_plasmid/utils/cdhit.py
ship_plasmid/utils/cluster_images.py
ship_plasmid/utils/clustering.py
ship_plasmid/utils/core_genes.py
ship_plasmid/utils/files.py
ship_plasmid/utils/genome.py
ship_plasmid/utils/interpretation.py
ship_plasmid/utils/jaccard.py
ship_plasmid/utils/markov_cluster.py
ship_plasmid/utils/motifs.py
ship_plasmid/utils/pangenome.py
ship_plasmid/utils/phylogeny.py
ship_plasmid/utils/plasmid_typing.py
ship_plasmid/utils/proteins.py
ship_plasmid-0.2.7.dist-info/entry_points.txt
ship_plasmid-0.2.7.dist-info/LICENSE
ship_plasmid-0.2.7.dist-info/WHEEL
ship_plasmid-0.2.7.dist-info/METADATA
ship_plasmid-0.2.7.dist-info/RECORD
